byu_ws_cli/__init__.py
byu_ws_cli/cli.py
byu_ws_cli/test/__init__.py
byu_ws_cli/test/test_cli.py
byu_ws_cli-0.9.9.data/data/LICENSE
byu_ws_cli-0.9.9.data/data/README.md
byu_ws_cli-0.9.9.data/scripts/call_byu_ws
byu_ws_cli-0.9.9.dist-info/DESCRIPTION.rst
byu_ws_cli-0.9.9.dist-info/METADATA
byu_ws_cli-0.9.9.dist-info/pydist.json
byu_ws_cli-0.9.9.dist-info/RECORD
byu_ws_cli-0.9.9.dist-info/top_level.txt
byu_ws_cli-0.9.9.dist-info/WHEEL
byu_ws_cli-0.9.9.dist-info/zip-safe
