Metadata-Version: 2.0
Name: byu-ws-cli
Version: 0.9.9
Summary: A command-line web service client for calling BYU REST web services.
Home-page: https://github.com/byu-oit-core-appeng/byu-ws-cli-python
Author: BYU OIT Core Application Engineering
Author-email: paul_eden@byu.edu
License: MIT
Platform: UNKNOWN
Obsoletes: oit_web_service_client
Requires-Dist: byu-ws-sdk (<1.1.0)
